nativize/__init__.py
nativize-0.1.0.dist-info/METADATA
nativize-0.1.0.dist-info/WHEEL
nativize-0.1.0.dist-info/RECORD
