Metadata-Version: 2.3
Name: nativize
Version: 0.1.0
Summary: 
Author: SimonRovder
Author-email: simon.rovder@gmail.com
Requires-Python: >=3.12
Classifier: Programming Language :: Python :: 3
Classifier: Programming Language :: Python :: 3.12
Classifier: Programming Language :: Python :: 3.13
